verbalized_sampling/__init__.py
verbalized_sampling/api.py
verbalized_sampling/cli.py
verbalized_sampling/pipeline.py
verbalized_sampling/selection.py
verbalized_sampling/analysis/dialogue_plots.py
verbalized_sampling/analysis/plots.py
verbalized_sampling/analysis/plotting.py
verbalized_sampling/analysis/evals/README.md
verbalized_sampling/analysis/evals/__init__.py
verbalized_sampling/analysis/evals/base.py
verbalized_sampling/analysis/evals/chi_square.py
verbalized_sampling/analysis/evals/creative_writing_v3.py
verbalized_sampling/analysis/evals/creativity_index.py
verbalized_sampling/analysis/evals/data_quality.py
verbalized_sampling/analysis/evals/data_quality_qa.py
verbalized_sampling/analysis/evals/diversity.py
verbalized_sampling/analysis/evals/factuality.py
verbalized_sampling/analysis/evals/joke_quality.py
verbalized_sampling/analysis/evals/length.py
verbalized_sampling/analysis/evals/ngram.py
verbalized_sampling/analysis/evals/quality.py
verbalized_sampling/analysis/evals/response_count.py
verbalized_sampling/analysis/evals/assets/cwv3_rubrics.py
verbalized_sampling/evals/accuracy.py
verbalized_sampling/evals/safety.py
verbalized_sampling/evals/dialogue/__init__.py
verbalized_sampling/evals/dialogue/donation.py
verbalized_sampling/evals/dialogue/linguistic.py
verbalized_sampling/examples/evaluation_demo.py
verbalized_sampling/examples/tasks_demo.py
verbalized_sampling/llms/__init__.py
verbalized_sampling/llms/base.py
verbalized_sampling/llms/embed.py
verbalized_sampling/llms/google.py
verbalized_sampling/llms/litellm.py
verbalized_sampling/llms/openai.py
verbalized_sampling/llms/openrouter.py
verbalized_sampling/llms/vllm.py
verbalized_sampling/methods/__init__.py
verbalized_sampling/methods/factory.py
verbalized_sampling/methods/parser.py
verbalized_sampling/methods/prompt.py
verbalized_sampling/methods/schema.py
verbalized_sampling/plots/README.md
verbalized_sampling/plots/__init__.py
verbalized_sampling/plots/base.py
verbalized_sampling-0.1.3.dist-info/METADATA
verbalized_sampling-0.1.3.dist-info/WHEEL
verbalized_sampling-0.1.3.dist-info/entry_points.txt
verbalized_sampling-0.1.3.dist-info/licenses/LICENSE.txt
verbalized_sampling-0.1.3.dist-info/RECORD
