Metadata-Version: 2.4
Name: verbalized-sampling
Version: 0.1.3
Summary: A library for running controlled experiments with LLMs using different sampling methods
Author-email: Simon Yu <yu.chi@northeastern.edu>, Jiayi Zhang <zhang.jiayi12@northeastern.edu>, Derek Chong <cderekch@stanford.edu>, Weiyan Shi <we.shi@northeastern.edu>
License: Apache-2.0
License-File: LICENSE.txt
Classifier: Development Status :: 3 - Alpha
Classifier: Intended Audience :: Science/Research
Classifier: License :: OSI Approved :: Apache Software License
Classifier: Programming Language :: Python :: 3
Classifier: Programming Language :: Python :: 3.8
Classifier: Programming Language :: Python :: 3.9
Classifier: Programming Language :: Python :: 3.10
Classifier: Programming Language :: Python :: 3.11
Classifier: Topic :: Scientific/Engineering :: Artificial Intelligence
Requires-Python: >=3.8
Requires-Dist: datasets
Requires-Dist: google-genai
Requires-Dist: litellm
Requires-Dist: matplotlib>=3.7.0
Requires-Dist: nltk
Requires-Dist: numpy<2.0.0,>=1.24
Requires-Dist: openai
Requires-Dist: openrouter>=0.1.0
Requires-Dist: rich>=13.0.0
Requires-Dist: sacremoses
Requires-Dist: scikit-learn
Requires-Dist: scipy>=1.10.0
Requires-Dist: seaborn
Requires-Dist: torch
Requires-Dist: tqdm>=4.65.0
Requires-Dist: transformers
Requires-Dist: typer>=0.9.0
Requires-Dist: unidecode
Provides-Extra: dev
Requires-Dist: black>=23.0; extra == 'dev'
Requires-Dist: isort>=5.0; extra == 'dev'
Requires-Dist: mypy>=1.0; extra == 'dev'
Requires-Dist: myst-parser>=2.0; extra == 'dev'
Requires-Dist: pytest>=7.0; extra == 'dev'
Requires-Dist: ruff>=0.1.0; extra == 'dev'
Requires-Dist: sphinx-autodoc-typehints>=1.0; extra == 'dev'
Requires-Dist: sphinx-rtd-theme>=1.0; extra == 'dev'
Requires-Dist: sphinx>=7.0; extra == 'dev'
Provides-Extra: gpu
Requires-Dist: vllm>=0.8.0; extra == 'gpu'
